{
  "current_date": "2026-06-13",
  "compared_to": {
    "since_league_day_1": "poe.ninja time machine label=day-1",
    "since_league_week_1": "poe.ninja time machine label=week-1"
  },
  "total_characters": {
    "current": 124243,
    "since_league_day_1": 74819,
    "since_league_week_1": 124264
  },
  "trends": {
    "class": {
      "since_league_day_1": {
        "rising": [
          {
            "name": "Titan",
            "current_pct": 24.18,
            "prev_pct": 0.81,
            "delta_pct_pts": 23.37,
            "current_count": 30048,
            "prev_count": 606,
            "delta_count": 29442
          },
          {
            "name": "Ritualist",
            "current_pct": 11.94,
            "prev_pct": 3.65,
            "delta_pct_pts": 8.29,
            "current_count": 14838,
            "prev_count": 2730,
            "delta_count": 12108
          },
          {
            "name": "Invoker",
            "current_pct": 5.2,
            "prev_pct": 0.47,
            "delta_pct_pts": 4.73,
            "current_count": 6455,
            "prev_count": 352,
            "delta_count": 6103
          },
          {
            "name": "Gemling Legionnaire",
            "current_pct": 4.15,
            "prev_pct": 0.47,
            "delta_pct_pts": 3.68,
            "current_count": 5150,
            "prev_count": 349,
            "delta_count": 4801
          },
          {
            "name": "Shaman",
            "current_pct": 3.9,
            "prev_pct": 1.24,
            "delta_pct_pts": 2.66,
            "current_count": 4848,
            "prev_count": 926,
            "delta_count": 3922
          },
          {
            "name": "Blood Mage",
            "current_pct": 2.84,
            "prev_pct": 1.51,
            "delta_pct_pts": 1.33,
            "current_count": 3527,
            "prev_count": 1131,
            "delta_count": 2396
          },
          {
            "name": "Disciple of Varashta",
            "current_pct": 1.79,
            "prev_pct": 0.54,
            "delta_pct_pts": 1.25,
            "current_count": 2225,
            "prev_count": 403,
            "delta_count": 1822
          },
          {
            "name": "Chronomancer",
            "current_pct": 2.12,
            "prev_pct": 1.11,
            "delta_pct_pts": 1.01,
            "current_count": 2632,
            "prev_count": 832,
            "delta_count": 1800
          },
          {
            "name": "Witchhunter",
            "current_pct": 3.3,
            "prev_pct": 2.32,
            "delta_pct_pts": 0.98,
            "current_count": 4094,
            "prev_count": 1736,
            "delta_count": 2358
          },
          {
            "name": "Lich",
            "current_pct": 2.46,
            "prev_pct": 1.51,
            "delta_pct_pts": 0.95,
            "current_count": 3054,
            "prev_count": 1128,
            "delta_count": 1926
          },
          {
            "name": "Tactician",
            "current_pct": 3.62,
            "prev_pct": 2.67,
            "delta_pct_pts": 0.95,
            "current_count": 4498,
            "prev_count": 1996,
            "delta_count": 2502
          },
          {
            "name": "Amazon",
            "current_pct": 1.1,
            "prev_pct": 0.56,
            "delta_pct_pts": 0.54,
            "current_count": 1366,
            "prev_count": 419,
            "delta_count": 947
          },
          {
            "name": "Warbringer",
            "current_pct": 1.65,
            "prev_pct": 1.25,
            "delta_pct_pts": 0.4,
            "current_count": 2054,
            "prev_count": 935,
            "delta_count": 1119
          }
        ],
        "falling": [
          {
            "name": "Deadeye",
            "current_pct": 1.22,
            "prev_pct": 12.49,
            "delta_pct_pts": -11.27,
            "current_count": 1510,
            "prev_count": 9344,
            "delta_count": -7834
          },
          {
            "name": "Smith of Kitava",
            "current_pct": 2.7,
            "prev_pct": 13.95,
            "delta_pct_pts": -11.25,
            "current_count": 3356,
            "prev_count": 10440,
            "delta_count": -7084
          },
          {
            "name": "Abyssal Lich",
            "current_pct": 0.25,
            "prev_pct": 4.45,
            "delta_pct_pts": -4.2,
            "current_count": 309,
            "prev_count": 3330,
            "delta_count": -3021
          },
          {
            "name": "Spirit Walker",
            "current_pct": 0.7,
            "prev_pct": 4.86,
            "delta_pct_pts": -4.16,
            "current_count": 869,
            "prev_count": 3633,
            "delta_count": -2764
          },
          {
            "name": "Pathfinder",
            "current_pct": 19.98,
            "prev_pct": 23.11,
            "delta_pct_pts": -3.13,
            "current_count": 24828,
            "prev_count": 17287,
            "delta_count": 7541
          },
          {
            "name": "Acolyte of Chayula",
            "current_pct": 0.62,
            "prev_pct": 3.7,
            "delta_pct_pts": -3.08,
            "current_count": 771,
            "prev_count": 2765,
            "delta_count": -1994
          },
          {
            "name": "#27",
            "current_pct": 0.0,
            "prev_pct": 2.76,
            "delta_pct_pts": -2.76,
            "current_count": 2,
            "prev_count": 2068,
            "delta_count": -2066
          },
          {
            "name": "Monk",
            "current_pct": 0.0,
            "prev_pct": 1.88,
            "delta_pct_pts": -1.88,
            "current_count": 5,
            "prev_count": 1403,
            "delta_count": -1398
          },
          {
            "name": "Huntress",
            "current_pct": 0.0,
            "prev_pct": 1.67,
            "delta_pct_pts": -1.67,
            "current_count": 1,
            "prev_count": 1249,
            "delta_count": -1248
          },
          {
            "name": "Witch",
            "current_pct": 0.0,
            "prev_pct": 1.33,
            "delta_pct_pts": -1.33,
            "current_count": 2,
            "prev_count": 995,
            "delta_count": -993
          },
          {
            "name": "#29",
            "current_pct": 0.0,
            "prev_pct": 1.04,
            "delta_pct_pts": -1.04,
            "current_count": 0,
            "prev_count": 777,
            "delta_count": -777
          },
          {
            "name": "Mercenary",
            "current_pct": 1.01,
            "prev_pct": 2.04,
            "delta_pct_pts": -1.03,
            "current_count": 1260,
            "prev_count": 1527,
            "delta_count": -267
          },
          {
            "name": "#30",
            "current_pct": 0.0,
            "prev_pct": 1.01,
            "delta_pct_pts": -1.01,
            "current_count": 0,
            "prev_count": 758,
            "delta_count": -758
          },
          {
            "name": "#28",
            "current_pct": 0.0,
            "prev_pct": 0.73,
            "delta_pct_pts": -0.73,
            "current_count": 1,
            "prev_count": 549,
            "delta_count": -548
          },
          {
            "name": "Sorceress",
            "current_pct": 1.11,
            "prev_pct": 1.7,
            "delta_pct_pts": -0.59,
            "current_count": 1374,
            "prev_count": 1271,
            "delta_count": 103
          }
        ]
      },
      "since_league_week_1": {
        "rising": [
          {
            "name": "Pathfinder",
            "current_pct": 19.98,
            "prev_pct": 14.48,
            "delta_pct_pts": 5.5,
            "current_count": 24828,
            "prev_count": 17999,
            "delta_count": 6829
          },
          {
            "name": "Witchhunter",
            "current_pct": 3.3,
            "prev_pct": 0.37,
            "delta_pct_pts": 2.93,
            "current_count": 4094,
            "prev_count": 465,
            "delta_count": 3629
          },
          {
            "name": "Invoker",
            "current_pct": 5.2,
            "prev_pct": 2.77,
            "delta_pct_pts": 2.43,
            "current_count": 6455,
            "prev_count": 3442,
            "delta_count": 3013
          },
          {
            "name": "Shaman",
            "current_pct": 3.9,
            "prev_pct": 2.71,
            "delta_pct_pts": 1.19,
            "current_count": 4848,
            "prev_count": 3365,
            "delta_count": 1483
          },
          {
            "name": "Stormweaver",
            "current_pct": 2.97,
            "prev_pct": 2.06,
            "delta_pct_pts": 0.91,
            "current_count": 3687,
            "prev_count": 2563,
            "delta_count": 1124
          },
          {
            "name": "Chronomancer",
            "current_pct": 2.12,
            "prev_pct": 1.32,
            "delta_pct_pts": 0.8,
            "current_count": 2632,
            "prev_count": 1637,
            "delta_count": 995
          },
          {
            "name": "Gemling Legionnaire",
            "current_pct": 4.15,
            "prev_pct": 3.45,
            "delta_pct_pts": 0.7,
            "current_count": 5150,
            "prev_count": 4288,
            "delta_count": 862
          },
          {
            "name": "Deadeye",
            "current_pct": 1.22,
            "prev_pct": 0.62,
            "delta_pct_pts": 0.6,
            "current_count": 1510,
            "prev_count": 775,
            "delta_count": 735
          },
          {
            "name": "Lich",
            "current_pct": 2.46,
            "prev_pct": 1.99,
            "delta_pct_pts": 0.47,
            "current_count": 3054,
            "prev_count": 2479,
            "delta_count": 575
          },
          {
            "name": "Sorceress",
            "current_pct": 1.11,
            "prev_pct": 0.75,
            "delta_pct_pts": 0.36,
            "current_count": 1374,
            "prev_count": 934,
            "delta_count": 440
          },
          {
            "name": "Warbringer",
            "current_pct": 1.65,
            "prev_pct": 1.4,
            "delta_pct_pts": 0.25,
            "current_count": 2054,
            "prev_count": 1741,
            "delta_count": 313
          },
          {
            "name": "Oracle",
            "current_pct": 1.19,
            "prev_pct": 1.0,
            "delta_pct_pts": 0.19,
            "current_count": 1476,
            "prev_count": 1243,
            "delta_count": 233
          },
          {
            "name": "Amazon",
            "current_pct": 1.1,
            "prev_pct": 0.94,
            "delta_pct_pts": 0.16,
            "current_count": 1366,
            "prev_count": 1163,
            "delta_count": 203
          }
        ],
        "falling": [
          {
            "name": "Ritualist",
            "current_pct": 11.94,
            "prev_pct": 18.12,
            "delta_pct_pts": -6.18,
            "current_count": 14838,
            "prev_count": 22517,
            "delta_count": -7679
          },
          {
            "name": "Abyssal Lich",
            "current_pct": 0.25,
            "prev_pct": 4.4,
            "delta_pct_pts": -4.15,
            "current_count": 309,
            "prev_count": 5467,
            "delta_count": -5158
          },
          {
            "name": "Blood Mage",
            "current_pct": 2.84,
            "prev_pct": 4.99,
            "delta_pct_pts": -2.15,
            "current_count": 3527,
            "prev_count": 6200,
            "delta_count": -2673
          },
          {
            "name": "Acolyte of Chayula",
            "current_pct": 0.62,
            "prev_pct": 2.38,
            "delta_pct_pts": -1.76,
            "current_count": 771,
            "prev_count": 2963,
            "delta_count": -2192
          },
          {
            "name": "Disciple of Varashta",
            "current_pct": 1.79,
            "prev_pct": 2.53,
            "delta_pct_pts": -0.74,
            "current_count": 2225,
            "prev_count": 3138,
            "delta_count": -913
          },
          {
            "name": "Titan",
            "current_pct": 24.18,
            "prev_pct": 24.88,
            "delta_pct_pts": -0.7,
            "current_count": 30048,
            "prev_count": 30916,
            "delta_count": -868
          },
          {
            "name": "Tactician",
            "current_pct": 3.62,
            "prev_pct": 4.05,
            "delta_pct_pts": -0.43,
            "current_count": 4498,
            "prev_count": 5035,
            "delta_count": -537
          },
          {
            "name": "Spirit Walker",
            "current_pct": 0.7,
            "prev_pct": 0.86,
            "delta_pct_pts": -0.16,
            "current_count": 869,
            "prev_count": 1068,
            "delta_count": -199
          },
          {
            "name": "Mercenary",
            "current_pct": 1.01,
            "prev_pct": 1.15,
            "delta_pct_pts": -0.14,
            "current_count": 1260,
            "prev_count": 1426,
            "delta_count": -166
          },
          {
            "name": "Smith of Kitava",
            "current_pct": 2.7,
            "prev_pct": 2.71,
            "delta_pct_pts": -0.01,
            "current_count": 3356,
            "prev_count": 3364,
            "delta_count": -8
          }
        ]
      }
    },
    "weaponmode": {
      "since_league_day_1": {
        "rising": [
          {
            "name": "Spear",
            "current_pct": 12.64,
            "prev_pct": 1.67,
            "delta_pct_pts": 10.97,
            "current_count": 15708,
            "prev_count": 1249,
            "delta_count": 14459
          },
          {
            "name": "Quarterstaff",
            "current_pct": 17.15,
            "prev_pct": 11.39,
            "delta_pct_pts": 5.76,
            "current_count": 21302,
            "prev_count": 8522,
            "delta_count": 12780
          },
          {
            "name": "Crossbow",
            "current_pct": 7.14,
            "prev_pct": 1.5,
            "delta_pct_pts": 5.64,
            "current_count": 8870,
            "prev_count": 1126,
            "delta_count": 7744
          },
          {
            "name": "Wand / Focus",
            "current_pct": 3.42,
            "prev_pct": 0.74,
            "delta_pct_pts": 2.68,
            "current_count": 4252,
            "prev_count": 555,
            "delta_count": 3697
          },
          {
            "name": "Unknown",
            "current_pct": 5.22,
            "prev_pct": 2.56,
            "delta_pct_pts": 2.66,
            "current_count": 6490,
            "prev_count": 1916,
            "delta_count": 4574
          },
          {
            "name": "Talisman",
            "current_pct": 2.64,
            "prev_pct": 0.07,
            "delta_pct_pts": 2.57,
            "current_count": 3282,
            "prev_count": 53,
            "delta_count": 3229
          },
          {
            "name": "Two Handed Mace / Sceptre",
            "current_pct": 2.29,
            "prev_pct": 0.16,
            "delta_pct_pts": 2.13,
            "current_count": 2847,
            "prev_count": 122,
            "delta_count": 2725
          },
          {
            "name": "Sceptre / Focus",
            "current_pct": 4.5,
            "prev_pct": 3.44,
            "delta_pct_pts": 1.06,
            "current_count": 5594,
            "prev_count": 2572,
            "delta_count": 3022
          },
          {
            "name": "Talisman / Sceptre",
            "current_pct": 0.9,
            "prev_pct": 0.11,
            "delta_pct_pts": 0.79,
            "current_count": 1116,
            "prev_count": 83,
            "delta_count": 1033
          },
          {
            "name": "Sceptre / Shield",
            "current_pct": 0.96,
            "prev_pct": 0.26,
            "delta_pct_pts": 0.7,
            "current_count": 1196,
            "prev_count": 192,
            "delta_count": 1004
          },
          {
            "name": "Staff / Focus",
            "current_pct": 0.9,
            "prev_pct": 0.24,
            "delta_pct_pts": 0.66,
            "current_count": 1121,
            "prev_count": 176,
            "delta_count": 945
          },
          {
            "name": "Unknown / Sceptre",
            "current_pct": 8.26,
            "prev_pct": 7.61,
            "delta_pct_pts": 0.65,
            "current_count": 10262,
            "prev_count": 5693,
            "delta_count": 4569
          },
          {
            "name": "Unarmed",
            "current_pct": 0.57,
            "prev_pct": 0.02,
            "delta_pct_pts": 0.55,
            "current_count": 704,
            "prev_count": 15,
            "delta_count": 689
          },
          {
            "name": "Sceptre / Buckler",
            "current_pct": 0.26,
            "prev_pct": 0.01,
            "delta_pct_pts": 0.25,
            "current_count": 323,
            "prev_count": 7,
            "delta_count": 316
          },
          {
            "name": "Spear / Shield",
            "current_pct": 0.2,
            "prev_pct": 0.0,
            "delta_pct_pts": 0.2,
            "current_count": 243,
            "prev_count": 0,
            "delta_count": 243
          }
        ],
        "falling": [
          {
            "name": "Two Handed Mace / Shield",
            "current_pct": 0.38,
            "prev_pct": 12.56,
            "delta_pct_pts": -12.18,
            "current_count": 466,
            "prev_count": 9399,
            "delta_count": -8933
          },
          {
            "name": "Mace / Shield",
            "current_pct": 1.05,
            "prev_pct": 8.58,
            "delta_pct_pts": -7.53,
            "current_count": 1308,
            "prev_count": 6422,
            "delta_count": -5114
          },
          {
            "name": "Dual Mace",
            "current_pct": 0.79,
            "prev_pct": 7.52,
            "delta_pct_pts": -6.73,
            "current_count": 987,
            "prev_count": 5626,
            "delta_count": -4639
          },
          {
            "name": "Spear / Sceptre",
            "current_pct": 2.95,
            "prev_pct": 5.63,
            "delta_pct_pts": -2.68,
            "current_count": 3659,
            "prev_count": 4212,
            "delta_count": -553
          },
          {
            "name": "Wand / Unknown",
            "current_pct": 0.59,
            "prev_pct": 3.14,
            "delta_pct_pts": -2.55,
            "current_count": 736,
            "prev_count": 2348,
            "delta_count": -1612
          },
          {
            "name": "Mace",
            "current_pct": 0.32,
            "prev_pct": 2.31,
            "delta_pct_pts": -1.99,
            "current_count": 397,
            "prev_count": 1726,
            "delta_count": -1329
          },
          {
            "name": "Bow / Quiver",
            "current_pct": 12.66,
            "prev_pct": 14.32,
            "delta_pct_pts": -1.66,
            "current_count": 15723,
            "prev_count": 10714,
            "delta_count": 5009
          },
          {
            "name": "Unknown / Focus",
            "current_pct": 0.21,
            "prev_pct": 1.12,
            "delta_pct_pts": -0.91,
            "current_count": 264,
            "prev_count": 840,
            "delta_count": -576
          },
          {
            "name": "Staff",
            "current_pct": 7.26,
            "prev_pct": 7.74,
            "delta_pct_pts": -0.48,
            "current_count": 9015,
            "prev_count": 5794,
            "delta_count": 3221
          },
          {
            "name": "Unknown / Buckler",
            "current_pct": 0.17,
            "prev_pct": 0.39,
            "delta_pct_pts": -0.22,
            "current_count": 210,
            "prev_count": 290,
            "delta_count": -80
          },
          {
            "name": "Dual Unknown",
            "current_pct": 0.32,
            "prev_pct": 0.49,
            "delta_pct_pts": -0.17,
            "current_count": 397,
            "prev_count": 363,
            "delta_count": 34
          },
          {
            "name": "Wand / Buckler",
            "current_pct": 0.34,
            "prev_pct": 0.5,
            "delta_pct_pts": -0.16,
            "current_count": 419,
            "prev_count": 377,
            "delta_count": 42
          },
          {
            "name": "Dual Two Handed Mace",
            "current_pct": 0.03,
            "prev_pct": 0.1,
            "delta_pct_pts": -0.07,
            "current_count": 39,
            "prev_count": 78,
            "delta_count": -39
          },
          {
            "name": "Sceptre / Unknown",
            "current_pct": 0.14,
            "prev_pct": 0.2,
            "delta_pct_pts": -0.06,
            "current_count": 178,
            "prev_count": 146,
            "delta_count": 32
          },
          {
            "name": "Sceptre",
            "current_pct": 0.11,
            "prev_pct": 0.17,
            "delta_pct_pts": -0.06,
            "current_count": 131,
            "prev_count": 130,
            "delta_count": 1
          }
        ]
      },
      "since_league_week_1": {
        "rising": [
          {
            "name": "Quarterstaff",
            "current_pct": 17.15,
            "prev_pct": 0.79,
            "delta_pct_pts": 16.36,
            "current_count": 21302,
            "prev_count": 983,
            "delta_count": 20319
          },
          {
            "name": "Unknown / Sceptre",
            "current_pct": 8.26,
            "prev_pct": 3.38,
            "delta_pct_pts": 4.88,
            "current_count": 10262,
            "prev_count": 4195,
            "delta_count": 6067
          },
          {
            "name": "Crossbow",
            "current_pct": 7.14,
            "prev_pct": 2.87,
            "delta_pct_pts": 4.27,
            "current_count": 8870,
            "prev_count": 3562,
            "delta_count": 5308
          },
          {
            "name": "Wand / Sceptre",
            "current_pct": 4.41,
            "prev_pct": 1.27,
            "delta_pct_pts": 3.14,
            "current_count": 5482,
            "prev_count": 1572,
            "delta_count": 3910
          },
          {
            "name": "Bow / Quiver",
            "current_pct": 12.66,
            "prev_pct": 10.09,
            "delta_pct_pts": 2.57,
            "current_count": 15723,
            "prev_count": 12542,
            "delta_count": 3181
          },
          {
            "name": "Spear",
            "current_pct": 12.64,
            "prev_pct": 10.39,
            "delta_pct_pts": 2.25,
            "current_count": 15708,
            "prev_count": 12907,
            "delta_count": 2801
          },
          {
            "name": "Sceptre / Focus",
            "current_pct": 4.5,
            "prev_pct": 3.56,
            "delta_pct_pts": 0.94,
            "current_count": 5594,
            "prev_count": 4425,
            "delta_count": 1169
          },
          {
            "name": "Talisman / Sceptre",
            "current_pct": 0.9,
            "prev_pct": 0.26,
            "delta_pct_pts": 0.64,
            "current_count": 1116,
            "prev_count": 323,
            "delta_count": 793
          },
          {
            "name": "Staff / Focus",
            "current_pct": 0.9,
            "prev_pct": 0.32,
            "delta_pct_pts": 0.58,
            "current_count": 1121,
            "prev_count": 392,
            "delta_count": 729
          },
          {
            "name": "Unarmed",
            "current_pct": 0.57,
            "prev_pct": 0.05,
            "delta_pct_pts": 0.52,
            "current_count": 704,
            "prev_count": 61,
            "delta_count": 643
          },
          {
            "name": "Dual Mace",
            "current_pct": 0.79,
            "prev_pct": 0.37,
            "delta_pct_pts": 0.42,
            "current_count": 987,
            "prev_count": 454,
            "delta_count": 533
          },
          {
            "name": "Dual Unknown",
            "current_pct": 0.32,
            "prev_pct": 0.06,
            "delta_pct_pts": 0.26,
            "current_count": 397,
            "prev_count": 76,
            "delta_count": 321
          },
          {
            "name": "Sceptre / Buckler",
            "current_pct": 0.26,
            "prev_pct": 0.01,
            "delta_pct_pts": 0.25,
            "current_count": 323,
            "prev_count": 10,
            "delta_count": 313
          },
          {
            "name": "Wand / Buckler",
            "current_pct": 0.34,
            "prev_pct": 0.12,
            "delta_pct_pts": 0.22,
            "current_count": 419,
            "prev_count": 143,
            "delta_count": 276
          },
          {
            "name": "Spear / Shield",
            "current_pct": 0.2,
            "prev_pct": 0.02,
            "delta_pct_pts": 0.18,
            "current_count": 243,
            "prev_count": 19,
            "delta_count": 224
          }
        ],
        "falling": [
          {
            "name": "Staff",
            "current_pct": 7.26,
            "prev_pct": 19.74,
            "delta_pct_pts": -12.48,
            "current_count": 9015,
            "prev_count": 24535,
            "delta_count": -15520
          },
          {
            "name": "Unknown",
            "current_pct": 5.22,
            "prev_pct": 14.67,
            "delta_pct_pts": -9.45,
            "current_count": 6490,
            "prev_count": 18226,
            "delta_count": -11736
          },
          {
            "name": "Spear / Sceptre",
            "current_pct": 2.95,
            "prev_pct": 7.05,
            "delta_pct_pts": -4.1,
            "current_count": 3659,
            "prev_count": 8757,
            "delta_count": -5098
          },
          {
            "name": "Wand / Focus",
            "current_pct": 3.42,
            "prev_pct": 6.99,
            "delta_pct_pts": -3.57,
            "current_count": 4252,
            "prev_count": 8681,
            "delta_count": -4429
          },
          {
            "name": "Mace",
            "current_pct": 0.32,
            "prev_pct": 3.23,
            "delta_pct_pts": -2.91,
            "current_count": 397,
            "prev_count": 4010,
            "delta_count": -3613
          },
          {
            "name": "Two Handed Mace / Sceptre",
            "current_pct": 2.29,
            "prev_pct": 3.94,
            "delta_pct_pts": -1.65,
            "current_count": 2847,
            "prev_count": 4902,
            "delta_count": -2055
          },
          {
            "name": "Mace / Sceptre",
            "current_pct": 0.03,
            "prev_pct": 1.21,
            "delta_pct_pts": -1.18,
            "current_count": 33,
            "prev_count": 1507,
            "delta_count": -1474
          },
          {
            "name": "Bow",
            "current_pct": 0.08,
            "prev_pct": 0.81,
            "delta_pct_pts": -0.73,
            "current_count": 95,
            "prev_count": 1010,
            "delta_count": -915
          },
          {
            "name": "Talisman",
            "current_pct": 2.64,
            "prev_pct": 3.23,
            "delta_pct_pts": -0.59,
            "current_count": 3282,
            "prev_count": 4015,
            "delta_count": -733
          },
          {
            "name": "Sceptre / Shield",
            "current_pct": 0.96,
            "prev_pct": 1.48,
            "delta_pct_pts": -0.52,
            "current_count": 1196,
            "prev_count": 1841,
            "delta_count": -645
          },
          {
            "name": "Mace / Shield",
            "current_pct": 1.05,
            "prev_pct": 1.32,
            "delta_pct_pts": -0.27,
            "current_count": 1308,
            "prev_count": 1644,
            "delta_count": -336
          },
          {
            "name": "Sceptre / Unknown",
            "current_pct": 0.14,
            "prev_pct": 0.33,
            "delta_pct_pts": -0.19,
            "current_count": 178,
            "prev_count": 409,
            "delta_count": -231
          },
          {
            "name": "Sceptre",
            "current_pct": 0.11,
            "prev_pct": 0.24,
            "delta_pct_pts": -0.13,
            "current_count": 131,
            "prev_count": 300,
            "delta_count": -169
          },
          {
            "name": "Mace / Buckler",
            "current_pct": 0.01,
            "prev_pct": 0.12,
            "delta_pct_pts": -0.11,
            "current_count": 7,
            "prev_count": 153,
            "delta_count": -146
          },
          {
            "name": "Wand",
            "current_pct": 0.07,
            "prev_pct": 0.18,
            "delta_pct_pts": -0.11,
            "current_count": 84,
            "prev_count": 228,
            "delta_count": -144
          }
        ]
      }
    },
    "items": {
      "since_league_day_1": {
        "rising": [
          {
            "name": "Rare Ring",
            "current_pct": 96.26,
            "prev_pct": 1.7,
            "delta_pct_pts": 94.56,
            "current_count": 119599,
            "prev_count": 1270,
            "delta_count": 118329
          },
          {
            "name": "Rare Boots",
            "current_pct": 92.35,
            "prev_pct": 0.0,
            "delta_pct_pts": 92.35,
            "current_count": 114743,
            "prev_count": 0,
            "delta_count": 114743
          },
          {
            "name": "Rare Jewel",
            "current_pct": 94.7,
            "prev_pct": 4.54,
            "delta_pct_pts": 90.16,
            "current_count": 117658,
            "prev_count": 3400,
            "delta_count": 114258
          },
          {
            "name": "Magic Flask",
            "current_pct": 92.81,
            "prev_pct": 16.7,
            "delta_pct_pts": 76.11,
            "current_count": 115309,
            "prev_count": 12498,
            "delta_count": 102811
          },
          {
            "name": "Rare Belt",
            "current_pct": 56.55,
            "prev_pct": 0.0,
            "delta_pct_pts": 56.55,
            "current_count": 70262,
            "prev_count": 0,
            "delta_count": 70262
          },
          {
            "name": "Nascent Hope",
            "current_pct": 52.19,
            "prev_pct": 0.0,
            "delta_pct_pts": 52.19,
            "current_count": 64838,
            "prev_count": 0,
            "delta_count": 64838
          },
          {
            "name": "Rare Helmet",
            "current_pct": 76.82,
            "prev_pct": 24.81,
            "delta_pct_pts": 52.01,
            "current_count": 95448,
            "prev_count": 18563,
            "delta_count": 76885
          },
          {
            "name": "Lavianga's Spirits",
            "current_pct": 50.63,
            "prev_pct": 0.0,
            "delta_pct_pts": 50.63,
            "current_count": 62899,
            "prev_count": 0,
            "delta_count": 62899
          },
          {
            "name": "The Fall of the Axe",
            "current_pct": 33.83,
            "prev_pct": 0.0,
            "delta_pct_pts": 33.83,
            "current_count": 42030,
            "prev_count": 0,
            "delta_count": 42030
          },
          {
            "name": "Beira's Anguish",
            "current_pct": 22.73,
            "prev_pct": 0.0,
            "delta_pct_pts": 22.73,
            "current_count": 28236,
            "prev_count": 0,
            "delta_count": 28236
          },
          {
            "name": "Magic Charm",
            "current_pct": 66.42,
            "prev_pct": 43.87,
            "delta_pct_pts": 22.55,
            "current_count": 82520,
            "prev_count": 32826,
            "delta_count": 49694
          },
          {
            "name": "From Nothing",
            "current_pct": 18.94,
            "prev_pct": 0.0,
            "delta_pct_pts": 18.94,
            "current_count": 23528,
            "prev_count": 0,
            "delta_count": 23528
          },
          {
            "name": "Rare Sceptre",
            "current_pct": 15.42,
            "prev_pct": 0.0,
            "delta_pct_pts": 15.42,
            "current_count": 19162,
            "prev_count": 0,
            "delta_count": 19162
          },
          {
            "name": "Rite of Passage",
            "current_pct": 19.64,
            "prev_pct": 5.47,
            "delta_pct_pts": 14.17,
            "current_count": 24400,
            "prev_count": 4089,
            "delta_count": 20311
          },
          {
            "name": "The Taming",
            "current_pct": 13.19,
            "prev_pct": 0.0,
            "delta_pct_pts": 13.19,
            "current_count": 16393,
            "prev_count": 0,
            "delta_count": 16393
          }
        ],
        "falling": [
          {
            "name": "Defiance of Destiny",
            "current_pct": 0.0,
            "prev_pct": 86.27,
            "delta_pct_pts": -86.27,
            "current_count": 0,
            "prev_count": 64543,
            "delta_count": -64543
          },
          {
            "name": "The Black Insignia",
            "current_pct": 0.0,
            "prev_pct": 82.83,
            "delta_pct_pts": -82.83,
            "current_count": 0,
            "prev_count": 61974,
            "delta_count": -61974
          },
          {
            "name": "Mageblood",
            "current_pct": 9.72,
            "prev_pct": 81.41,
            "delta_pct_pts": -71.69,
            "current_count": 12079,
            "prev_count": 60911,
            "delta_count": -48832
          },
          {
            "name": "Skysliver",
            "current_pct": 10.68,
            "prev_pct": 81.14,
            "delta_pct_pts": -70.46,
            "current_count": 13270,
            "prev_count": 60708,
            "delta_count": -47438
          },
          {
            "name": "The Ordained",
            "current_pct": 9.27,
            "prev_pct": 75.07,
            "delta_pct_pts": -65.8,
            "current_count": 11514,
            "prev_count": 56168,
            "delta_count": -44654
          },
          {
            "name": "Amor Mandragora",
            "current_pct": 11.63,
            "prev_pct": 47.72,
            "delta_pct_pts": -36.09,
            "current_count": 14447,
            "prev_count": 35702,
            "delta_count": -21255
          },
          {
            "name": "Waveshaper",
            "current_pct": 0.0,
            "prev_pct": 32.97,
            "delta_pct_pts": -32.97,
            "current_count": 0,
            "prev_count": 24667,
            "delta_count": -24667
          },
          {
            "name": "Rare Body Armour",
            "current_pct": 66.28,
            "prev_pct": 95.37,
            "delta_pct_pts": -29.09,
            "current_count": 82348,
            "prev_count": 71352,
            "delta_count": 10996
          },
          {
            "name": "Heart of the Well",
            "current_pct": 60.39,
            "prev_pct": 87.61,
            "delta_pct_pts": -27.22,
            "current_count": 75029,
            "prev_count": 65550,
            "delta_count": 9479
          },
          {
            "name": "The Brass Dome",
            "current_pct": 0.0,
            "prev_pct": 21.06,
            "delta_pct_pts": -21.06,
            "current_count": 0,
            "prev_count": 15755,
            "delta_count": -15755
          },
          {
            "name": "Palm of the Dreamer",
            "current_pct": 0.0,
            "prev_pct": 19.9,
            "delta_pct_pts": -19.9,
            "current_count": 0,
            "prev_count": 14891,
            "delta_count": -14891
          },
          {
            "name": "Normal Body Armour",
            "current_pct": 0.0,
            "prev_pct": 13.86,
            "delta_pct_pts": -13.86,
            "current_count": 0,
            "prev_count": 10370,
            "delta_count": -10370
          },
          {
            "name": "Forgotten Warden",
            "current_pct": 0.0,
            "prev_pct": 12.85,
            "delta_pct_pts": -12.85,
            "current_count": 0,
            "prev_count": 9612,
            "delta_count": -9612
          },
          {
            "name": "Normal Vaal Body Part",
            "current_pct": 0.0,
            "prev_pct": 8.78,
            "delta_pct_pts": -8.78,
            "current_count": 0,
            "prev_count": 6569,
            "delta_count": -6569
          },
          {
            "name": "Rare Two Handed Mace",
            "current_pct": 0.0,
            "prev_pct": 8.03,
            "delta_pct_pts": -8.03,
            "current_count": 0,
            "prev_count": 6009,
            "delta_count": -6009
          }
        ]
      },
      "since_league_week_1": {
        "rising": [
          {
            "name": "Rare Belt",
            "current_pct": 56.55,
            "prev_pct": 0.0,
            "delta_pct_pts": 56.55,
            "current_count": 70262,
            "prev_count": 0,
            "delta_count": 70262
          },
          {
            "name": "Nascent Hope",
            "current_pct": 52.19,
            "prev_pct": 9.35,
            "delta_pct_pts": 42.84,
            "current_count": 64838,
            "prev_count": 11619,
            "delta_count": 53219
          },
          {
            "name": "Lavianga's Spirits",
            "current_pct": 50.63,
            "prev_pct": 14.42,
            "delta_pct_pts": 36.21,
            "current_count": 62899,
            "prev_count": 17917,
            "delta_count": 44982
          },
          {
            "name": "Heart of the Well",
            "current_pct": 60.39,
            "prev_pct": 31.42,
            "delta_pct_pts": 28.97,
            "current_count": 75029,
            "prev_count": 39045,
            "delta_count": 35984
          },
          {
            "name": "The Fall of the Axe",
            "current_pct": 33.83,
            "prev_pct": 8.83,
            "delta_pct_pts": 25.0,
            "current_count": 42030,
            "prev_count": 10975,
            "delta_count": 31055
          },
          {
            "name": "Rare Quarterstaff",
            "current_pct": 18.11,
            "prev_pct": 0.0,
            "delta_pct_pts": 18.11,
            "current_count": 22498,
            "prev_count": 0,
            "delta_count": 22498
          },
          {
            "name": "Beira's Anguish",
            "current_pct": 22.73,
            "prev_pct": 6.67,
            "delta_pct_pts": 16.06,
            "current_count": 28236,
            "prev_count": 8284,
            "delta_count": 19952
          },
          {
            "name": "Rite of Passage",
            "current_pct": 19.64,
            "prev_pct": 4.97,
            "delta_pct_pts": 14.67,
            "current_count": 24400,
            "prev_count": 6170,
            "delta_count": 18230
          },
          {
            "name": "From Nothing",
            "current_pct": 18.94,
            "prev_pct": 4.9,
            "delta_pct_pts": 14.04,
            "current_count": 23528,
            "prev_count": 6095,
            "delta_count": 17433
          },
          {
            "name": "Rare Bow",
            "current_pct": 12.48,
            "prev_pct": 0.0,
            "delta_pct_pts": 12.48,
            "current_count": 15511,
            "prev_count": 0,
            "delta_count": 15511
          },
          {
            "name": "Amor Mandragora",
            "current_pct": 11.63,
            "prev_pct": 0.0,
            "delta_pct_pts": 11.63,
            "current_count": 14447,
            "prev_count": 0,
            "delta_count": 14447
          },
          {
            "name": "Magic Sceptre",
            "current_pct": 10.68,
            "prev_pct": 0.0,
            "delta_pct_pts": 10.68,
            "current_count": 13270,
            "prev_count": 0,
            "delta_count": 13270
          },
          {
            "name": "Cadiro's Gambit",
            "current_pct": 10.25,
            "prev_pct": 0.0,
            "delta_pct_pts": 10.25,
            "current_count": 12730,
            "prev_count": 0,
            "delta_count": 12730
          },
          {
            "name": "Headhunter",
            "current_pct": 9.87,
            "prev_pct": 0.0,
            "delta_pct_pts": 9.87,
            "current_count": 12264,
            "prev_count": 0,
            "delta_count": 12264
          },
          {
            "name": "Mageblood",
            "current_pct": 9.72,
            "prev_pct": 0.0,
            "delta_pct_pts": 9.72,
            "current_count": 12079,
            "prev_count": 0,
            "delta_count": 12079
          }
        ],
        "falling": [
          {
            "name": "Blood of the Warrior",
            "current_pct": 7.56,
            "prev_pct": 74.18,
            "delta_pct_pts": -66.62,
            "current_count": 9396,
            "prev_count": 92185,
            "delta_count": -82789
          },
          {
            "name": "Rare Two Handed Mace",
            "current_pct": 0.0,
            "prev_pct": 25.16,
            "delta_pct_pts": -25.16,
            "current_count": 0,
            "prev_count": 31261,
            "delta_count": -31261
          },
          {
            "name": "Morior Invictus",
            "current_pct": 6.26,
            "prev_pct": 29.02,
            "delta_pct_pts": -22.76,
            "current_count": 7776,
            "prev_count": 36064,
            "delta_count": -28288
          },
          {
            "name": "Liminal Coil",
            "current_pct": 0.0,
            "prev_pct": 20.26,
            "delta_pct_pts": -20.26,
            "current_count": 0,
            "prev_count": 25181,
            "delta_count": -25181
          },
          {
            "name": "Ming's Heart",
            "current_pct": 0.0,
            "prev_pct": 18.2,
            "delta_pct_pts": -18.2,
            "current_count": 0,
            "prev_count": 22620,
            "delta_count": -22620
          },
          {
            "name": "Magic Charm",
            "current_pct": 66.42,
            "prev_pct": 84.58,
            "delta_pct_pts": -18.16,
            "current_count": 82520,
            "prev_count": 105099,
            "delta_count": -22579
          },
          {
            "name": "Constricting Command",
            "current_pct": 0.0,
            "prev_pct": 14.67,
            "delta_pct_pts": -14.67,
            "current_count": 0,
            "prev_count": 18227,
            "delta_count": -18227
          },
          {
            "name": "Undying Hate",
            "current_pct": 0.0,
            "prev_pct": 12.87,
            "delta_pct_pts": -12.87,
            "current_count": 0,
            "prev_count": 15992,
            "delta_count": -15992
          },
          {
            "name": "Rare Body Armour",
            "current_pct": 66.28,
            "prev_pct": 78.54,
            "delta_pct_pts": -12.26,
            "current_count": 82348,
            "prev_count": 97600,
            "delta_count": -15252
          },
          {
            "name": "Silks of Veneration",
            "current_pct": 0.0,
            "prev_pct": 10.09,
            "delta_pct_pts": -10.09,
            "current_count": 0,
            "prev_count": 12534,
            "delta_count": -12534
          },
          {
            "name": "Nebuloch",
            "current_pct": 0.0,
            "prev_pct": 9.03,
            "delta_pct_pts": -9.03,
            "current_count": 0,
            "prev_count": 11220,
            "delta_count": -11220
          },
          {
            "name": "Loreweave",
            "current_pct": 0.0,
            "prev_pct": 8.32,
            "delta_pct_pts": -8.32,
            "current_count": 0,
            "prev_count": 10336,
            "delta_count": -10336
          },
          {
            "name": "Uhtred's Chalice",
            "current_pct": 0.0,
            "prev_pct": 8.31,
            "delta_pct_pts": -8.31,
            "current_count": 0,
            "prev_count": 10329,
            "delta_count": -10329
          },
          {
            "name": "Valako's Roar",
            "current_pct": 0.0,
            "prev_pct": 7.89,
            "delta_pct_pts": -7.89,
            "current_count": 0,
            "prev_count": 9808,
            "delta_count": -9808
          },
          {
            "name": "Olroth's Resolve",
            "current_pct": 0.0,
            "prev_pct": 7.13,
            "delta_pct_pts": -7.13,
            "current_count": 0,
            "prev_count": 8865,
            "delta_count": -8865
          }
        ]
      }
    },
    "skills": {
      "since_league_day_1": {
        "rising": [
          {
            "name": "Herald of Ice",
            "current_pct": 30.73,
            "prev_pct": 0.0,
            "delta_pct_pts": 30.73,
            "current_count": 38174,
            "prev_count": 0,
            "delta_count": 38174
          },
          {
            "name": "Harmonic Remnants II",
            "current_pct": 27.36,
            "prev_pct": 0.0,
            "delta_pct_pts": 27.36,
            "current_count": 33996,
            "prev_count": 0,
            "delta_count": 33996
          },
          {
            "name": "Barrage",
            "current_pct": 23.81,
            "prev_pct": 0.0,
            "delta_pct_pts": 23.81,
            "current_count": 29582,
            "prev_count": 0,
            "delta_count": 29582
          },
          {
            "name": "Hollow Focus",
            "current_pct": 20.52,
            "prev_pct": 0.0,
            "delta_pct_pts": 20.52,
            "current_count": 25495,
            "prev_count": 0,
            "delta_count": 25495
          },
          {
            "name": "Shock",
            "current_pct": 19.71,
            "prev_pct": 0.0,
            "delta_pct_pts": 19.71,
            "current_count": 24493,
            "prev_count": 0,
            "delta_count": 24493
          },
          {
            "name": "Elemental Weakness",
            "current_pct": 19.42,
            "prev_pct": 0.0,
            "delta_pct_pts": 19.42,
            "current_count": 24134,
            "prev_count": 0,
            "delta_count": 24134
          },
          {
            "name": "Remnant Potency III",
            "current_pct": 17.13,
            "prev_pct": 0.0,
            "delta_pct_pts": 17.13,
            "current_count": 21284,
            "prev_count": 0,
            "delta_count": 21284
          },
          {
            "name": "Lightning Penetration",
            "current_pct": 16.61,
            "prev_pct": 0.0,
            "delta_pct_pts": 16.61,
            "current_count": 20631,
            "prev_count": 0,
            "delta_count": 20631
          },
          {
            "name": "Lightning Attunement",
            "current_pct": 15.15,
            "prev_pct": 0.0,
            "delta_pct_pts": 15.15,
            "current_count": 18823,
            "prev_count": 0,
            "delta_count": 18823
          },
          {
            "name": "Refutation",
            "current_pct": 14.76,
            "prev_pct": 0.0,
            "delta_pct_pts": 14.76,
            "current_count": 18342,
            "prev_count": 0,
            "delta_count": 18342
          },
          {
            "name": "Whirling Slash",
            "current_pct": 14.54,
            "prev_pct": 0.0,
            "delta_pct_pts": 14.54,
            "current_count": 18066,
            "prev_count": 0,
            "delta_count": 18066
          },
          {
            "name": "Quarterstaff Strike",
            "current_pct": 14.33,
            "prev_pct": 0.0,
            "delta_pct_pts": 14.33,
            "current_count": 17802,
            "prev_count": 0,
            "delta_count": 17802
          },
          {
            "name": "Twister",
            "current_pct": 13.96,
            "prev_pct": 0.0,
            "delta_pct_pts": 13.96,
            "current_count": 17339,
            "prev_count": 0,
            "delta_count": 17339
          },
          {
            "name": "Frozen Spite",
            "current_pct": 13.9,
            "prev_pct": 0.0,
            "delta_pct_pts": 13.9,
            "current_count": 17272,
            "prev_count": 0,
            "delta_count": 17272
          },
          {
            "name": "Pounce",
            "current_pct": 13.52,
            "prev_pct": 0.0,
            "delta_pct_pts": 13.52,
            "current_count": 16795,
            "prev_count": 0,
            "delta_count": 16795
          }
        ],
        "falling": [
          {
            "name": "Heightened Accuracy II",
            "current_pct": 0.0,
            "prev_pct": 14.43,
            "delta_pct_pts": -14.43,
            "current_count": 0,
            "prev_count": 10798,
            "delta_count": -10798
          },
          {
            "name": "Rage III",
            "current_pct": 0.0,
            "prev_pct": 13.6,
            "delta_pct_pts": -13.6,
            "current_count": 0,
            "prev_count": 10172,
            "delta_count": -10172
          },
          {
            "name": "Blazing Critical",
            "current_pct": 0.0,
            "prev_pct": 10.63,
            "delta_pct_pts": -10.63,
            "current_count": 0,
            "prev_count": 7954,
            "delta_count": -7954
          },
          {
            "name": "Her Declaration",
            "current_pct": 0.0,
            "prev_pct": 10.37,
            "delta_pct_pts": -10.37,
            "current_count": 0,
            "prev_count": 7755,
            "delta_count": -7755
          },
          {
            "name": "Prolonged Duration II",
            "current_pct": 0.0,
            "prev_pct": 10.2,
            "delta_pct_pts": -10.2,
            "current_count": 0,
            "prev_count": 7635,
            "delta_count": -7635
          },
          {
            "name": "Helbrym's Hide",
            "current_pct": 0.0,
            "prev_pct": 7.91,
            "delta_pct_pts": -7.91,
            "current_count": 0,
            "prev_count": 5921,
            "delta_count": -5921
          },
          {
            "name": "Ferocious Roar",
            "current_pct": 0.0,
            "prev_pct": 6.2,
            "delta_pct_pts": -6.2,
            "current_count": 0,
            "prev_count": 4640,
            "delta_count": -4640
          },
          {
            "name": "Raging Cry",
            "current_pct": 0.0,
            "prev_pct": 5.63,
            "delta_pct_pts": -5.63,
            "current_count": 0,
            "prev_count": 4211,
            "delta_count": -4211
          },
          {
            "name": "Rapid Attacks III",
            "current_pct": 0.0,
            "prev_pct": 5.19,
            "delta_pct_pts": -5.19,
            "current_count": 0,
            "prev_count": 3883,
            "delta_count": -3883
          },
          {
            "name": "Malice",
            "current_pct": 0.0,
            "prev_pct": 4.69,
            "delta_pct_pts": -4.69,
            "current_count": 0,
            "prev_count": 3510,
            "delta_count": -3510
          },
          {
            "name": "Molten Blast",
            "current_pct": 0.0,
            "prev_pct": 4.58,
            "delta_pct_pts": -4.58,
            "current_count": 0,
            "prev_count": 3430,
            "delta_count": -3430
          },
          {
            "name": "Blindside",
            "current_pct": 0.0,
            "prev_pct": 4.4,
            "delta_pct_pts": -4.4,
            "current_count": 0,
            "prev_count": 3291,
            "delta_count": -3291
          },
          {
            "name": "Ember Fusillade",
            "current_pct": 0.0,
            "prev_pct": 4.27,
            "delta_pct_pts": -4.27,
            "current_count": 0,
            "prev_count": 3195,
            "delta_count": -3195
          },
          {
            "name": "Mysticism II",
            "current_pct": 0.0,
            "prev_pct": 4.27,
            "delta_pct_pts": -4.27,
            "current_count": 0,
            "prev_count": 3197,
            "delta_count": -3197
          },
          {
            "name": "Disengage",
            "current_pct": 0.0,
            "prev_pct": 4.18,
            "delta_pct_pts": -4.18,
            "current_count": 0,
            "prev_count": 3130,
            "delta_count": -3130
          }
        ]
      },
      "since_league_week_1": {
        "rising": [
          {
            "name": "Harmonic Remnants II",
            "current_pct": 27.36,
            "prev_pct": 0.0,
            "delta_pct_pts": 27.36,
            "current_count": 33996,
            "prev_count": 0,
            "delta_count": 33996
          },
          {
            "name": "Shock",
            "current_pct": 19.71,
            "prev_pct": 0.0,
            "delta_pct_pts": 19.71,
            "current_count": 24493,
            "prev_count": 0,
            "delta_count": 24493
          },
          {
            "name": "Elemental Weakness",
            "current_pct": 19.42,
            "prev_pct": 0.0,
            "delta_pct_pts": 19.42,
            "current_count": 24134,
            "prev_count": 0,
            "delta_count": 24134
          },
          {
            "name": "Remnant Potency III",
            "current_pct": 17.13,
            "prev_pct": 0.0,
            "delta_pct_pts": 17.13,
            "current_count": 21284,
            "prev_count": 0,
            "delta_count": 21284
          },
          {
            "name": "Lightning Attunement",
            "current_pct": 15.15,
            "prev_pct": 0.0,
            "delta_pct_pts": 15.15,
            "current_count": 18823,
            "prev_count": 0,
            "delta_count": 18823
          },
          {
            "name": "Refutation",
            "current_pct": 14.76,
            "prev_pct": 0.0,
            "delta_pct_pts": 14.76,
            "current_count": 18342,
            "prev_count": 0,
            "delta_count": 18342
          },
          {
            "name": "Quarterstaff Strike",
            "current_pct": 14.33,
            "prev_pct": 0.0,
            "delta_pct_pts": 14.33,
            "current_count": 17802,
            "prev_count": 0,
            "delta_count": 17802
          },
          {
            "name": "Frozen Spite",
            "current_pct": 13.9,
            "prev_pct": 0.0,
            "delta_pct_pts": 13.9,
            "current_count": 17272,
            "prev_count": 0,
            "delta_count": 17272
          },
          {
            "name": "Culmination II",
            "current_pct": 13.0,
            "prev_pct": 0.0,
            "delta_pct_pts": 13.0,
            "current_count": 16154,
            "prev_count": 0,
            "delta_count": 16154
          },
          {
            "name": "Wind Dancer",
            "current_pct": 12.36,
            "prev_pct": 0.0,
            "delta_pct_pts": 12.36,
            "current_count": 15351,
            "prev_count": 0,
            "delta_count": 15351
          },
          {
            "name": "Cackling Companions",
            "current_pct": 11.81,
            "prev_pct": 0.0,
            "delta_pct_pts": 11.81,
            "current_count": 14670,
            "prev_count": 0,
            "delta_count": 14670
          },
          {
            "name": "Cluster Grenade",
            "current_pct": 10.77,
            "prev_pct": 0.0,
            "delta_pct_pts": 10.77,
            "current_count": 13381,
            "prev_count": 0,
            "delta_count": 13381
          },
          {
            "name": "Chaotic Freeze",
            "current_pct": 10.71,
            "prev_pct": 0.0,
            "delta_pct_pts": 10.71,
            "current_count": 13302,
            "prev_count": 0,
            "delta_count": 13302
          },
          {
            "name": "Withering Presence",
            "current_pct": 10.66,
            "prev_pct": 0.0,
            "delta_pct_pts": 10.66,
            "current_count": 13243,
            "prev_count": 0,
            "delta_count": 13243
          },
          {
            "name": "Lightning Exposure",
            "current_pct": 10.62,
            "prev_pct": 0.0,
            "delta_pct_pts": 10.62,
            "current_count": 13195,
            "prev_count": 0,
            "delta_count": 13195
          }
        ],
        "falling": [
          {
            "name": "Perpetual Charge",
            "current_pct": 0.0,
            "prev_pct": 20.59,
            "delta_pct_pts": -20.59,
            "current_count": 0,
            "prev_count": 25584,
            "delta_count": -25584
          },
          {
            "name": "Mana Remnants",
            "current_pct": 0.0,
            "prev_pct": 19.21,
            "delta_pct_pts": -19.21,
            "current_count": 0,
            "prev_count": 23873,
            "delta_count": -23873
          },
          {
            "name": "Armour Demolisher II",
            "current_pct": 0.0,
            "prev_pct": 18.5,
            "delta_pct_pts": -18.5,
            "current_count": 0,
            "prev_count": 22990,
            "delta_count": -22990
          },
          {
            "name": "Wild Protector",
            "current_pct": 0.0,
            "prev_pct": 15.58,
            "delta_pct_pts": -15.58,
            "current_count": 0,
            "prev_count": 19357,
            "delta_count": -19357
          },
          {
            "name": "Explosive Grenade",
            "current_pct": 0.0,
            "prev_pct": 14.97,
            "delta_pct_pts": -14.97,
            "current_count": 0,
            "prev_count": 18597,
            "delta_count": -18597
          },
          {
            "name": "Burgeon II",
            "current_pct": 0.0,
            "prev_pct": 14.79,
            "delta_pct_pts": -14.79,
            "current_count": 0,
            "prev_count": 18373,
            "delta_count": -18373
          },
          {
            "name": "Tornado Shot",
            "current_pct": 0.0,
            "prev_pct": 14.29,
            "delta_pct_pts": -14.29,
            "current_count": 0,
            "prev_count": 17756,
            "delta_count": -17756
          },
          {
            "name": "Comet",
            "current_pct": 0.0,
            "prev_pct": 13.74,
            "delta_pct_pts": -13.74,
            "current_count": 0,
            "prev_count": 17071,
            "delta_count": -17071
          },
          {
            "name": "Uhtred's Constellation",
            "current_pct": 0.0,
            "prev_pct": 12.94,
            "delta_pct_pts": -12.94,
            "current_count": 0,
            "prev_count": 16081,
            "delta_count": -16081
          },
          {
            "name": "Encase in Jade",
            "current_pct": 0.0,
            "prev_pct": 12.78,
            "delta_pct_pts": -12.78,
            "current_count": 0,
            "prev_count": 15879,
            "delta_count": -15879
          },
          {
            "name": "Mirage Deadeye",
            "current_pct": 0.0,
            "prev_pct": 12.29,
            "delta_pct_pts": -12.29,
            "current_count": 0,
            "prev_count": 15274,
            "delta_count": -15274
          },
          {
            "name": "Time Freeze",
            "current_pct": 0.0,
            "prev_pct": 11.06,
            "delta_pct_pts": -11.06,
            "current_count": 0,
            "prev_count": 13749,
            "delta_count": -13749
          },
          {
            "name": "Mana Flare",
            "current_pct": 0.0,
            "prev_pct": 10.94,
            "delta_pct_pts": -10.94,
            "current_count": 0,
            "prev_count": 13600,
            "delta_count": -13600
          },
          {
            "name": "Prolonged Duration II",
            "current_pct": 0.0,
            "prev_pct": 10.12,
            "delta_pct_pts": -10.12,
            "current_count": 0,
            "prev_count": 12575,
            "delta_count": -12575
          },
          {
            "name": "Navira, the Last Mirage",
            "current_pct": 0.0,
            "prev_pct": 9.49,
            "delta_pct_pts": -9.49,
            "current_count": 0,
            "prev_count": 11794,
            "delta_count": -11794
          }
        ]
      }
    },
    "skillmodes": {
      "since_league_day_1": {
        "rising": [
          {
            "name": "Normal",
            "current_pct": 99.86,
            "prev_pct": 81.75,
            "delta_pct_pts": 18.11,
            "current_count": 124074,
            "prev_count": 61161,
            "delta_count": 62913
          },
          {
            "name": "Triggered",
            "current_pct": 14.89,
            "prev_pct": 1.57,
            "delta_pct_pts": 13.32,
            "current_count": 18496,
            "prev_count": 1178,
            "delta_count": 17318
          }
        ],
        "falling": []
      },
      "since_league_week_1": {
        "rising": [
          {
            "name": "Triggered",
            "current_pct": 14.89,
            "prev_pct": 11.1,
            "delta_pct_pts": 3.79,
            "current_count": 18496,
            "prev_count": 13799,
            "delta_count": 4697
          },
          {
            "name": "Normal",
            "current_pct": 99.86,
            "prev_pct": 99.81,
            "delta_pct_pts": 0.05,
            "current_count": 124074,
            "prev_count": 124032,
            "delta_count": 42
          }
        ],
        "falling": []
      }
    },
    "keypassives": {
      "since_league_day_1": {
        "rising": [
          {
            "name": "Way of the Stonefist",
            "current_pct": 24.06,
            "prev_pct": 0.0,
            "delta_pct_pts": 24.06,
            "current_count": 29897,
            "prev_count": 0,
            "delta_count": 29897
          },
          {
            "name": "Runic Meridians",
            "current_pct": 20.35,
            "prev_pct": 0.0,
            "delta_pct_pts": 20.35,
            "current_count": 25284,
            "prev_count": 0,
            "delta_count": 25284
          },
          {
            "name": "Hollow Focus Technique",
            "current_pct": 20.04,
            "prev_pct": 0.0,
            "delta_pct_pts": 20.04,
            "current_count": 24896,
            "prev_count": 0,
            "delta_count": 24896
          },
          {
            "name": "Hollow Palm Technique",
            "current_pct": 20.59,
            "prev_pct": 1.44,
            "delta_pct_pts": 19.15,
            "current_count": 25582,
            "prev_count": 1078,
            "delta_count": 24504
          },
          {
            "name": "Wild Protector",
            "current_pct": 19.79,
            "prev_pct": 1.1,
            "delta_pct_pts": 18.69,
            "current_count": 24585,
            "prev_count": 825,
            "delta_count": 23760
          },
          {
            "name": "Dance with Death",
            "current_pct": 14.19,
            "prev_pct": 0.0,
            "delta_pct_pts": 14.19,
            "current_count": 17629,
            "prev_count": 0,
            "delta_count": 17629
          },
          {
            "name": "Constant Gale",
            "current_pct": 13.85,
            "prev_pct": 0.0,
            "delta_pct_pts": 13.85,
            "current_count": 17204,
            "prev_count": 0,
            "delta_count": 17204
          },
          {
            "name": "Gathering Winds",
            "current_pct": 11.59,
            "prev_pct": 0.0,
            "delta_pct_pts": 11.59,
            "current_count": 14401,
            "prev_count": 0,
            "delta_count": 14401
          },
          {
            "name": "Primal Bounty",
            "current_pct": 11.04,
            "prev_pct": 0.0,
            "delta_pct_pts": 11.04,
            "current_count": 13718,
            "prev_count": 0,
            "delta_count": 13718
          },
          {
            "name": "Projectile Proximity Specialisation",
            "current_pct": 10.98,
            "prev_pct": 0.0,
            "delta_pct_pts": 10.98,
            "current_count": 13640,
            "prev_count": 0,
            "delta_count": 13640
          },
          {
            "name": "Endless Munitions",
            "current_pct": 10.87,
            "prev_pct": 0.0,
            "delta_pct_pts": 10.87,
            "current_count": 13507,
            "prev_count": 0,
            "delta_count": 13507
          },
          {
            "name": "Mystic Attunement",
            "current_pct": 10.36,
            "prev_pct": 0.0,
            "delta_pct_pts": 10.36,
            "current_count": 12874,
            "prev_count": 0,
            "delta_count": 12874
          },
          {
            "name": "Idolatry",
            "current_pct": 9.04,
            "prev_pct": 0.0,
            "delta_pct_pts": 9.04,
            "current_count": 11230,
            "prev_count": 0,
            "delta_count": 11230
          },
          {
            "name": "Motoric Implants",
            "current_pct": 9.03,
            "prev_pct": 0.0,
            "delta_pct_pts": 9.03,
            "current_count": 11222,
            "prev_count": 0,
            "delta_count": 11222
          },
          {
            "name": "Implanted Gems",
            "current_pct": 8.83,
            "prev_pct": 0.0,
            "delta_pct_pts": 8.83,
            "current_count": 10965,
            "prev_count": 0,
            "delta_count": 10965
          }
        ],
        "falling": [
          {
            "name": "Bringer of Flame",
            "current_pct": 0.0,
            "prev_pct": 16.78,
            "delta_pct_pts": -16.78,
            "current_count": 0,
            "prev_count": 12555,
            "delta_count": -12555
          },
          {
            "name": "Kitavan Engraving",
            "current_pct": 0.0,
            "prev_pct": 13.57,
            "delta_pct_pts": -13.57,
            "current_count": 0,
            "prev_count": 10155,
            "delta_count": -10155
          },
          {
            "name": "Support Straps",
            "current_pct": 0.0,
            "prev_pct": 10.84,
            "delta_pct_pts": -10.84,
            "current_count": 0,
            "prev_count": 8107,
            "delta_count": -8107
          },
          {
            "name": "Mysterious Lineage",
            "current_pct": 0.0,
            "prev_pct": 10.28,
            "delta_pct_pts": -10.28,
            "current_count": 0,
            "prev_count": 7691,
            "delta_count": -7691
          },
          {
            "name": "Resonance",
            "current_pct": 0.0,
            "prev_pct": 10.24,
            "delta_pct_pts": -10.24,
            "current_count": 0,
            "prev_count": 7664,
            "delta_count": -7664
          },
          {
            "name": "Dedication to Kitava",
            "current_pct": 0.0,
            "prev_pct": 7.92,
            "delta_pct_pts": -7.92,
            "current_count": 0,
            "prev_count": 5926,
            "delta_count": -5926
          },
          {
            "name": "Heat of the Forge",
            "current_pct": 0.0,
            "prev_pct": 7.43,
            "delta_pct_pts": -7.43,
            "current_count": 0,
            "prev_count": 5556,
            "delta_count": -5556
          },
          {
            "name": "The Lesser Harm",
            "current_pct": 5.18,
            "prev_pct": 10.92,
            "delta_pct_pts": -5.74,
            "current_count": 6432,
            "prev_count": 8173,
            "delta_count": -1741
          },
          {
            "name": "Primal Hunger",
            "current_pct": 0.0,
            "prev_pct": 5.26,
            "delta_pct_pts": -5.26,
            "current_count": 0,
            "prev_count": 3938,
            "delta_count": -3938
          },
          {
            "name": "Heatproofing",
            "current_pct": 0.0,
            "prev_pct": 5.19,
            "delta_pct_pts": -5.19,
            "current_count": 0,
            "prev_count": 3881,
            "delta_count": -3881
          },
          {
            "name": "Internal Layer",
            "current_pct": 0.0,
            "prev_pct": 4.29,
            "delta_pct_pts": -4.29,
            "current_count": 0,
            "prev_count": 3209,
            "delta_count": -3209
          },
          {
            "name": "Incessant Cacophony",
            "current_pct": 0.0,
            "prev_pct": 4.02,
            "delta_pct_pts": -4.02,
            "current_count": 0,
            "prev_count": 3011,
            "delta_count": -3011
          },
          {
            "name": "Blood Magic",
            "current_pct": 0.0,
            "prev_pct": 3.68,
            "delta_pct_pts": -3.68,
            "current_count": 0,
            "prev_count": 2750,
            "delta_count": -2750
          },
          {
            "name": "Smith's Masterwork",
            "current_pct": 0.0,
            "prev_pct": 3.5,
            "delta_pct_pts": -3.5,
            "current_count": 0,
            "prev_count": 2622,
            "delta_count": -2622
          },
          {
            "name": "Beidat's Gaze",
            "current_pct": 0.0,
            "prev_pct": 3.38,
            "delta_pct_pts": -3.38,
            "current_count": 0,
            "prev_count": 2530,
            "delta_count": -2530
          }
        ]
      },
      "since_league_week_1": {
        "rising": [
          {
            "name": "Constant Gale",
            "current_pct": 13.85,
            "prev_pct": 0.0,
            "delta_pct_pts": 13.85,
            "current_count": 17204,
            "prev_count": 0,
            "delta_count": 17204
          },
          {
            "name": "The Mhacha's Gift",
            "current_pct": 10.65,
            "prev_pct": 0.0,
            "delta_pct_pts": 10.65,
            "current_count": 13230,
            "prev_count": 0,
            "delta_count": 13230
          },
          {
            "name": "Mystic Attunement",
            "current_pct": 10.36,
            "prev_pct": 0.0,
            "delta_pct_pts": 10.36,
            "current_count": 12874,
            "prev_count": 0,
            "delta_count": 12874
          },
          {
            "name": "Sacred Unity",
            "current_pct": 10.33,
            "prev_pct": 0.0,
            "delta_pct_pts": 10.33,
            "current_count": 12833,
            "prev_count": 0,
            "delta_count": 12833
          },
          {
            "name": "Wild Protector",
            "current_pct": 19.79,
            "prev_pct": 10.17,
            "delta_pct_pts": 9.62,
            "current_count": 24585,
            "prev_count": 12640,
            "delta_count": 11945
          },
          {
            "name": "Idolatry",
            "current_pct": 9.04,
            "prev_pct": 0.0,
            "delta_pct_pts": 9.04,
            "current_count": 11230,
            "prev_count": 0,
            "delta_count": 11230
          },
          {
            "name": "Motoric Implants",
            "current_pct": 9.03,
            "prev_pct": 0.0,
            "delta_pct_pts": 9.03,
            "current_count": 11222,
            "prev_count": 0,
            "delta_count": 11222
          },
          {
            "name": "Hollow Palm Technique",
            "current_pct": 20.59,
            "prev_pct": 11.71,
            "delta_pct_pts": 8.88,
            "current_count": 25582,
            "prev_count": 14554,
            "delta_count": 11028
          },
          {
            "name": "Implanted Gems",
            "current_pct": 8.83,
            "prev_pct": 0.0,
            "delta_pct_pts": 8.83,
            "current_count": 10965,
            "prev_count": 0,
            "delta_count": 10965
          },
          {
            "name": "Scarred Faith",
            "current_pct": 6.24,
            "prev_pct": 0.0,
            "delta_pct_pts": 6.24,
            "current_count": 7750,
            "prev_count": 0,
            "delta_count": 7750
          },
          {
            "name": "Stay Light, Use Cover",
            "current_pct": 5.22,
            "prev_pct": 0.0,
            "delta_pct_pts": 5.22,
            "current_count": 6480,
            "prev_count": 0,
            "delta_count": 6480
          },
          {
            "name": "The Lesser Harm",
            "current_pct": 5.18,
            "prev_pct": 0.0,
            "delta_pct_pts": 5.18,
            "current_count": 6432,
            "prev_count": 0,
            "delta_count": 6432
          },
          {
            "name": "Entwined Realities",
            "current_pct": 5.16,
            "prev_pct": 0.0,
            "delta_pct_pts": 5.16,
            "current_count": 6407,
            "prev_count": 0,
            "delta_count": 6407
          },
          {
            "name": "Mind Over Matter",
            "current_pct": 4.85,
            "prev_pct": 0.0,
            "delta_pct_pts": 4.85,
            "current_count": 6026,
            "prev_count": 0,
            "delta_count": 6026
          },
          {
            "name": "Advanced Thaumaturgy",
            "current_pct": 7.67,
            "prev_pct": 2.95,
            "delta_pct_pts": 4.72,
            "current_count": 9524,
            "prev_count": 3667,
            "delta_count": 5857
          }
        ],
        "falling": [
          {
            "name": "Ancestral Bond",
            "current_pct": 0.0,
            "prev_pct": 14.56,
            "delta_pct_pts": -14.56,
            "current_count": 0,
            "prev_count": 18092,
            "delta_count": -18092
          },
          {
            "name": "Resonance",
            "current_pct": 0.0,
            "prev_pct": 13.49,
            "delta_pct_pts": -13.49,
            "current_count": 0,
            "prev_count": 16760,
            "delta_count": -16760
          },
          {
            "name": "Sacrifice of Flesh",
            "current_pct": 0.0,
            "prev_pct": 13.13,
            "delta_pct_pts": -13.13,
            "current_count": 0,
            "prev_count": 16320,
            "delta_count": -16320
          },
          {
            "name": "Iron Reflexes",
            "current_pct": 0.0,
            "prev_pct": 9.3,
            "delta_pct_pts": -9.3,
            "current_count": 0,
            "prev_count": 11556,
            "delta_count": -11556
          },
          {
            "name": "Whoever Pays Best",
            "current_pct": 0.0,
            "prev_pct": 8.11,
            "delta_pct_pts": -8.11,
            "current_count": 0,
            "prev_count": 10080,
            "delta_count": -10080
          },
          {
            "name": "Necromantic Conduit",
            "current_pct": 0.0,
            "prev_pct": 7.99,
            "delta_pct_pts": -7.99,
            "current_count": 0,
            "prev_count": 9927,
            "delta_count": -9927
          },
          {
            "name": "Watch How I Do It",
            "current_pct": 0.0,
            "prev_pct": 7.13,
            "delta_pct_pts": -7.13,
            "current_count": 0,
            "prev_count": 8855,
            "delta_count": -8855
          },
          {
            "name": "Endless Munitions",
            "current_pct": 10.87,
            "prev_pct": 16.73,
            "delta_pct_pts": -5.86,
            "current_count": 13507,
            "prev_count": 20784,
            "delta_count": -7277
          },
          {
            "name": "Bringer of the Apocalypse",
            "current_pct": 0.0,
            "prev_pct": 5.36,
            "delta_pct_pts": -5.36,
            "current_count": 0,
            "prev_count": 6656,
            "delta_count": -6656
          },
          {
            "name": "Pain Attunement",
            "current_pct": 0.0,
            "prev_pct": 4.75,
            "delta_pct_pts": -4.75,
            "current_count": 0,
            "prev_count": 5898,
            "delta_count": -5898
          },
          {
            "name": "Faith is a Choice",
            "current_pct": 0.0,
            "prev_pct": 4.3,
            "delta_pct_pts": -4.3,
            "current_count": 0,
            "prev_count": 5341,
            "delta_count": -5341
          },
          {
            "name": "Black Scythe Training",
            "current_pct": 0.0,
            "prev_pct": 4.04,
            "delta_pct_pts": -4.04,
            "current_count": 0,
            "prev_count": 5021,
            "delta_count": -5021
          },
          {
            "name": "The Unseen Path",
            "current_pct": 0.0,
            "prev_pct": 3.65,
            "delta_pct_pts": -3.65,
            "current_count": 0,
            "prev_count": 4537,
            "delta_count": -4537
          },
          {
            "name": "Blackened Heart",
            "current_pct": 0.0,
            "prev_pct": 3.62,
            "delta_pct_pts": -3.62,
            "current_count": 0,
            "prev_count": 4493,
            "delta_count": -4493
          },
          {
            "name": "Sanguimancy",
            "current_pct": 0.0,
            "prev_pct": 3.56,
            "delta_pct_pts": -3.56,
            "current_count": 0,
            "prev_count": 4428,
            "delta_count": -4428
          }
        ]
      }
    },
    "anointed": {
      "since_league_day_1": {
        "rising": [
          {
            "name": "Focused Thrust",
            "current_pct": 10.13,
            "prev_pct": 0.0,
            "delta_pct_pts": 10.13,
            "current_count": 12581,
            "prev_count": 0,
            "delta_count": 12581
          },
          {
            "name": "Reaving",
            "current_pct": 6.54,
            "prev_pct": 0.0,
            "delta_pct_pts": 6.54,
            "current_count": 8130,
            "prev_count": 0,
            "delta_count": 8130
          },
          {
            "name": "The Frenzied Bear",
            "current_pct": 4.68,
            "prev_pct": 0.01,
            "delta_pct_pts": 4.67,
            "current_count": 5814,
            "prev_count": 7,
            "delta_count": 5807
          },
          {
            "name": "Barbaric Strength",
            "current_pct": 3.75,
            "prev_pct": 0.02,
            "delta_pct_pts": 3.73,
            "current_count": 4657,
            "prev_count": 12,
            "delta_count": 4645
          },
          {
            "name": "Lasting Trauma",
            "current_pct": 3.5,
            "prev_pct": 0.0,
            "delta_pct_pts": 3.5,
            "current_count": 4348,
            "prev_count": 2,
            "delta_count": 4346
          },
          {
            "name": "Evocational Practitioner",
            "current_pct": 2.99,
            "prev_pct": 0.01,
            "delta_pct_pts": 2.98,
            "current_count": 3715,
            "prev_count": 5,
            "delta_count": 3710
          },
          {
            "name": "Zarokh's Gift",
            "current_pct": 2.88,
            "prev_pct": 0.01,
            "delta_pct_pts": 2.87,
            "current_count": 3578,
            "prev_count": 4,
            "delta_count": 3574
          },
          {
            "name": "Growing Swarm",
            "current_pct": 2.47,
            "prev_pct": 0.0,
            "delta_pct_pts": 2.47,
            "current_count": 3075,
            "prev_count": 0,
            "delta_count": 3075
          },
          {
            "name": "Preservation",
            "current_pct": 2.03,
            "prev_pct": 0.01,
            "delta_pct_pts": 2.02,
            "current_count": 2527,
            "prev_count": 5,
            "delta_count": 2522
          },
          {
            "name": "Efficient Inscriptions",
            "current_pct": 1.68,
            "prev_pct": 0.0,
            "delta_pct_pts": 1.68,
            "current_count": 2088,
            "prev_count": 2,
            "delta_count": 2086
          },
          {
            "name": "Run and Gun",
            "current_pct": 1.59,
            "prev_pct": 0.0,
            "delta_pct_pts": 1.59,
            "current_count": 1973,
            "prev_count": 0,
            "delta_count": 1973
          },
          {
            "name": "Gem Enthusiast",
            "current_pct": 1.58,
            "prev_pct": 0.0,
            "delta_pct_pts": 1.58,
            "current_count": 1963,
            "prev_count": 0,
            "delta_count": 1963
          },
          {
            "name": "Dominion",
            "current_pct": 1.54,
            "prev_pct": 0.0,
            "delta_pct_pts": 1.54,
            "current_count": 1914,
            "prev_count": 3,
            "delta_count": 1911
          },
          {
            "name": "Wrapped Quiver",
            "current_pct": 1.33,
            "prev_pct": 0.0,
            "delta_pct_pts": 1.33,
            "current_count": 1658,
            "prev_count": 2,
            "delta_count": 1656
          },
          {
            "name": "Core of the Guardian",
            "current_pct": 1.25,
            "prev_pct": 0.0,
            "delta_pct_pts": 1.25,
            "current_count": 1557,
            "prev_count": 3,
            "delta_count": 1554
          }
        ],
        "falling": []
      },
      "since_league_week_1": {
        "rising": [
          {
            "name": "Focused Thrust",
            "current_pct": 10.13,
            "prev_pct": 0.0,
            "delta_pct_pts": 10.13,
            "current_count": 12581,
            "prev_count": 0,
            "delta_count": 12581
          },
          {
            "name": "Reaving",
            "current_pct": 6.54,
            "prev_pct": 0.0,
            "delta_pct_pts": 6.54,
            "current_count": 8130,
            "prev_count": 0,
            "delta_count": 8130
          },
          {
            "name": "The Frenzied Bear",
            "current_pct": 4.68,
            "prev_pct": 0.0,
            "delta_pct_pts": 4.68,
            "current_count": 5814,
            "prev_count": 0,
            "delta_count": 5814
          },
          {
            "name": "Lasting Trauma",
            "current_pct": 3.5,
            "prev_pct": 0.0,
            "delta_pct_pts": 3.5,
            "current_count": 4348,
            "prev_count": 0,
            "delta_count": 4348
          },
          {
            "name": "Evocational Practitioner",
            "current_pct": 2.99,
            "prev_pct": 0.22,
            "delta_pct_pts": 2.77,
            "current_count": 3715,
            "prev_count": 278,
            "delta_count": 3437
          },
          {
            "name": "Growing Swarm",
            "current_pct": 2.47,
            "prev_pct": 0.0,
            "delta_pct_pts": 2.47,
            "current_count": 3075,
            "prev_count": 0,
            "delta_count": 3075
          },
          {
            "name": "Preservation",
            "current_pct": 2.03,
            "prev_pct": 0.0,
            "delta_pct_pts": 2.03,
            "current_count": 2527,
            "prev_count": 0,
            "delta_count": 2527
          },
          {
            "name": "Barbaric Strength",
            "current_pct": 3.75,
            "prev_pct": 1.78,
            "delta_pct_pts": 1.97,
            "current_count": 4657,
            "prev_count": 2218,
            "delta_count": 2439
          },
          {
            "name": "Run and Gun",
            "current_pct": 1.59,
            "prev_pct": 0.0,
            "delta_pct_pts": 1.59,
            "current_count": 1973,
            "prev_count": 0,
            "delta_count": 1973
          },
          {
            "name": "Gem Enthusiast",
            "current_pct": 1.58,
            "prev_pct": 0.0,
            "delta_pct_pts": 1.58,
            "current_count": 1963,
            "prev_count": 0,
            "delta_count": 1963
          },
          {
            "name": "Dominion",
            "current_pct": 1.54,
            "prev_pct": 0.0,
            "delta_pct_pts": 1.54,
            "current_count": 1914,
            "prev_count": 0,
            "delta_count": 1914
          },
          {
            "name": "Efficient Inscriptions",
            "current_pct": 1.68,
            "prev_pct": 0.3,
            "delta_pct_pts": 1.38,
            "current_count": 2088,
            "prev_count": 371,
            "delta_count": 1717
          },
          {
            "name": "Wrapped Quiver",
            "current_pct": 1.33,
            "prev_pct": 0.0,
            "delta_pct_pts": 1.33,
            "current_count": 1658,
            "prev_count": 0,
            "delta_count": 1658
          },
          {
            "name": "Core of the Guardian",
            "current_pct": 1.25,
            "prev_pct": 0.0,
            "delta_pct_pts": 1.25,
            "current_count": 1557,
            "prev_count": 0,
            "delta_count": 1557
          },
          {
            "name": "Catapult",
            "current_pct": 1.05,
            "prev_pct": 0.0,
            "delta_pct_pts": 1.05,
            "current_count": 1309,
            "prev_count": 0,
            "delta_count": 1309
          }
        ],
        "falling": [
          {
            "name": "Inner Faith",
            "current_pct": 0.0,
            "prev_pct": 7.87,
            "delta_pct_pts": -7.87,
            "current_count": 0,
            "prev_count": 9780,
            "delta_count": -9780
          },
          {
            "name": "Zarokh's Gift",
            "current_pct": 2.88,
            "prev_pct": 5.71,
            "delta_pct_pts": -2.83,
            "current_count": 3578,
            "prev_count": 7097,
            "delta_count": -3519
          },
          {
            "name": "Ancient Aegis",
            "current_pct": 0.0,
            "prev_pct": 1.86,
            "delta_pct_pts": -1.86,
            "current_count": 0,
            "prev_count": 2316,
            "delta_count": -2316
          },
          {
            "name": "Killer Instinct",
            "current_pct": 0.0,
            "prev_pct": 1.82,
            "delta_pct_pts": -1.82,
            "current_count": 0,
            "prev_count": 2259,
            "delta_count": -2259
          },
          {
            "name": "Siphon",
            "current_pct": 0.0,
            "prev_pct": 1.82,
            "delta_pct_pts": -1.82,
            "current_count": 0,
            "prev_count": 2256,
            "delta_count": -2256
          },
          {
            "name": "Careful Assassin",
            "current_pct": 0.5,
            "prev_pct": 2.23,
            "delta_pct_pts": -1.73,
            "current_count": 623,
            "prev_count": 2774,
            "delta_count": -2151
          },
          {
            "name": "Necromantic Ward",
            "current_pct": 0.0,
            "prev_pct": 1.09,
            "delta_pct_pts": -1.09,
            "current_count": 0,
            "prev_count": 1350,
            "delta_count": -1350
          },
          {
            "name": "The Howling Primate",
            "current_pct": 0.0,
            "prev_pct": 1.02,
            "delta_pct_pts": -1.02,
            "current_count": 0,
            "prev_count": 1268,
            "delta_count": -1268
          },
          {
            "name": "Dark Entries",
            "current_pct": 0.0,
            "prev_pct": 0.97,
            "delta_pct_pts": -0.97,
            "current_count": 0,
            "prev_count": 1204,
            "delta_count": -1204
          },
          {
            "name": "Locked On",
            "current_pct": 0.0,
            "prev_pct": 0.84,
            "delta_pct_pts": -0.84,
            "current_count": 0,
            "prev_count": 1041,
            "delta_count": -1041
          },
          {
            "name": "Blood of Rage",
            "current_pct": 0.0,
            "prev_pct": 0.79,
            "delta_pct_pts": -0.79,
            "current_count": 0,
            "prev_count": 980,
            "delta_count": -980
          },
          {
            "name": "Short Shot",
            "current_pct": 0.0,
            "prev_pct": 0.69,
            "delta_pct_pts": -0.69,
            "current_count": 0,
            "prev_count": 854,
            "delta_count": -854
          },
          {
            "name": "Sling Shots",
            "current_pct": 0.0,
            "prev_pct": 0.58,
            "delta_pct_pts": -0.58,
            "current_count": 0,
            "prev_count": 722,
            "delta_count": -722
          },
          {
            "name": "Eroding Chains",
            "current_pct": 0.0,
            "prev_pct": 0.51,
            "delta_pct_pts": -0.51,
            "current_count": 0,
            "prev_count": 635,
            "delta_count": -635
          },
          {
            "name": "Ancestral Reach",
            "current_pct": 0.0,
            "prev_pct": 0.49,
            "delta_pct_pts": -0.49,
            "current_count": 0,
            "prev_count": 611,
            "delta_count": -611
          }
        ]
      }
    }
  }
}
